{
    "schemes": [
        "http"
    ],
    "swagger": "2.0",
    "info": {
        "description": "Dokumentasi Swagger e Slurr",
        "title": "PPOB Service",
        "termsOfService": "http://swagger.io/terms/",
        "contact": {},
        "license": {
            "name": "Apache 2.0",
            "url": "http://www.apache.org/licenses/LICENSE-2.0.html"
        },
        "version": "1.0"
    },
    "host": "localhost:1234",
    "basePath": "/",
    "paths": {
        "/v1/bestseller/{id}": {
            "get": {
                "description": "Get Best Seller each Category",
                "consumes": [
                    "application/json"
                ],
                "produces": [
                    "application/json"
                ],
                "tags": [
                    "Product"
                ],
                "summary": "Get Best Seller",
                "parameters": [
                    {
                        "type": "string",
                        "description": "id category",
                        "name": "id",
                        "in": "path",
                        "required": true
                    }
                ],
                "responses": {
                    "200": {
                        "description": "OK",
                        "schema": {
                            "$ref": "#/definitions/delivery.JSONSuccessResult"
                        }
                    },
                    "400": {
                        "description": "Bad Request",
                        "schema": {
                            "$ref": "#/definitions/delivery.JSONBadReqResult"
                        }
                    },
                    "500": {
                        "description": "Internal Server Error",
                        "schema": {
                            "$ref": "#/definitions/delivery.JSONInternalResult"
                        }
                    }
                }
            }
        },
        "/v1/category": {
            "get": {
                "description": "Get Random Tagihan Product",
                "consumes": [
                    "application/json"
                ],
                "produces": [
                    "application/json"
                ],
                "tags": [
                    "Category"
                ],
                "summary": "Get all Product w pagination",
                "responses": {
                    "200": {
                        "description": "OK",
                        "schema": {
                            "$ref": "#/definitions/delivery.JSONSuccessResult"
                        }
                    },
                    "400": {
                        "description": "Bad Request",
                        "schema": {
                            "$ref": "#/definitions/delivery.JSONBadReqResult"
                        }
                    },
                    "500": {
                        "description": "Internal Server Error",
                        "schema": {
                            "$ref": "#/definitions/delivery.JSONInternalResult"
                        }
                    }
                }
            },
            "post": {
                "security": [
                    {
                        "BearerAuth": []
                    }
                ],
                "description": "Edit Product via JSON",
                "consumes": [
                    "application/json"
                ],
                "produces": [
                    "application/json"
                ],
                "tags": [
                    "Category"
                ],
                "summary": "Create Product",
                "parameters": [
                    {
                        "description": "Product",
                        "name": "user",
                        "in": "body",
                        "required": true,
                        "schema": {
                            "$ref": "#/definitions/request.Category"
                        }
                    }
                ],
                "responses": {
                    "200": {
                        "description": "OK",
                        "schema": {
                            "$ref": "#/definitions/delivery.JSONSuccessResult"
                        }
                    },
                    "400": {
                        "description": "Bad Request",
                        "schema": {
                            "$ref": "#/definitions/delivery.JSONBadReqResult"
                        }
                    },
                    "500": {
                        "description": "Internal Server Error",
                        "schema": {
                            "$ref": "#/definitions/delivery.JSONInternalResult"
                        }
                    }
                }
            }
        },
        "/v1/category/{id}": {
            "delete": {
                "security": [
                    {
                        "BearerAuth": []
                    }
                ],
                "description": "Delete Product via ID",
                "consumes": [
                    "application/json"
                ],
                "produces": [
                    "application/json"
                ],
                "tags": [
                    "Category"
                ],
                "summary": "Delete Product",
                "parameters": [
                    {
                        "type": "string",
                        "description": "ID Category",
                        "name": "id",
                        "in": "path",
                        "required": true
                    }
                ],
                "responses": {
                    "200": {
                        "description": "OK",
                        "schema": {
                            "$ref": "#/definitions/delivery.JSONSuccessResult"
                        }
                    },
                    "400": {
                        "description": "Bad Request",
                        "schema": {
                            "$ref": "#/definitions/delivery.JSONBadReqResult"
                        }
                    },
                    "500": {
                        "description": "Internal Server Error",
                        "schema": {
                            "$ref": "#/definitions/delivery.JSONInternalResult"
                        }
                    }
                }
            }
        },
        "/v1/login": {
            "post": {
                "description": "login user to server with json.",
                "consumes": [
                    "multipart/form-data"
                ],
                "produces": [
                    "application/json"
                ],
                "tags": [
                    "User"
                ],
                "summary": "Login User to server",
                "parameters": [
                    {
                        "type": "string",
                        "default": "admin",
                        "description": "email",
                        "name": "email",
                        "in": "formData",
                        "required": true
                    },
                    {
                        "type": "string",
                        "default": "admin",
                        "description": "password",
                        "name": "password",
                        "in": "formData",
                        "required": true
                    }
                ],
                "responses": {
                    "200": {
                        "description": "OK",
                        "schema": {
                            "$ref": "#/definitions/delivery.JSONSuccessResult"
                        }
                    },
                    "400": {
                        "description": "Bad Request",
                        "schema": {
                            "$ref": "#/definitions/delivery.JSONBadReqResult"
                        }
                    },
                    "500": {
                        "description": "Internal Server Error",
                        "schema": {
                            "$ref": "#/definitions/delivery.JSONInternalResult"
                        }
                    }
                }
            }
        },
        "/v1/product": {
            "put": {
                "security": [
                    {
                        "BearerAuth": []
                    }
                ],
                "description": "Edit Product via JSON",
                "consumes": [
                    "application/json"
                ],
                "produces": [
                    "application/json"
                ],
                "tags": [
                    "Product"
                ],
                "summary": "Edit Product",
                "parameters": [
                    {
                        "description": "User Data",
                        "name": "user",
                        "in": "body",
                        "required": true,
                        "schema": {
                            "$ref": "#/definitions/request.EditProduct"
                        }
                    }
                ],
                "responses": {
                    "200": {
                        "description": "OK",
                        "schema": {
                            "$ref": "#/definitions/delivery.JSONSuccessResult"
                        }
                    },
                    "400": {
                        "description": "Bad Request",
                        "schema": {
                            "$ref": "#/definitions/delivery.JSONBadReqResult"
                        }
                    },
                    "500": {
                        "description": "Internal Server Error",
                        "schema": {
                            "$ref": "#/definitions/delivery.JSONInternalResult"
                        }
                    }
                }
            },
            "post": {
                "security": [
                    {
                        "BearerAuth": []
                    }
                ],
                "description": "Edit Product via JSON",
                "consumes": [
                    "application/json"
                ],
                "produces": [
                    "application/json"
                ],
                "tags": [
                    "Product"
                ],
                "summary": "Create Product",
                "parameters": [
                    {
                        "description": "Product",
                        "name": "user",
                        "in": "body",
                        "required": true,
                        "schema": {
                            "$ref": "#/definitions/request.CreateProduct"
                        }
                    }
                ],
                "responses": {
                    "200": {
                        "description": "OK",
                        "schema": {
                            "$ref": "#/definitions/delivery.JSONSuccessResult"
                        }
                    },
                    "400": {
                        "description": "Bad Request",
                        "schema": {
                            "$ref": "#/definitions/delivery.JSONBadReqResult"
                        }
                    },
                    "500": {
                        "description": "Internal Server Error",
                        "schema": {
                            "$ref": "#/definitions/delivery.JSONInternalResult"
                        }
                    }
                }
            }
        },
        "/v1/product/all": {
            "get": {
                "description": "Get Random Tagihan Product",
                "consumes": [
                    "application/json"
                ],
                "produces": [
                    "application/json"
                ],
                "tags": [
                    "Product"
                ],
                "summary": "Get all Product w pagination",
                "responses": {
                    "200": {
                        "description": "OK",
                        "schema": {
                            "$ref": "#/definitions/delivery.JSONSuccessResult"
                        }
                    },
                    "400": {
                        "description": "Bad Request",
                        "schema": {
                            "$ref": "#/definitions/delivery.JSONBadReqResult"
                        }
                    },
                    "500": {
                        "description": "Internal Server Error",
                        "schema": {
                            "$ref": "#/definitions/delivery.JSONInternalResult"
                        }
                    }
                }
            }
        },
        "/v1/product/pln": {
            "get": {
                "description": "Get Random Tagihan Product",
                "consumes": [
                    "application/json"
                ],
                "produces": [
                    "application/json"
                ],
                "tags": [
                    "Product"
                ],
                "summary": "Get Random Product",
                "responses": {
                    "200": {
                        "description": "OK",
                        "schema": {
                            "$ref": "#/definitions/delivery.JSONSuccessResult"
                        }
                    },
                    "400": {
                        "description": "Bad Request",
                        "schema": {
                            "$ref": "#/definitions/delivery.JSONBadReqResult"
                        }
                    },
                    "500": {
                        "description": "Internal Server Error",
                        "schema": {
                            "$ref": "#/definitions/delivery.JSONInternalResult"
                        }
                    }
                }
            }
        },
        "/v1/product/{id}": {
            "get": {
                "description": "Get Product via Param",
                "consumes": [
                    "application/json"
                ],
                "produces": [
                    "application/json"
                ],
                "tags": [
                    "Product"
                ],
                "summary": "GetProduct via Params",
                "parameters": [
                    {
                        "type": "integer",
                        "description": "ID Category",
                        "name": "id",
                        "in": "path",
                        "required": true
                    }
                ],
                "responses": {
                    "200": {
                        "description": "OK",
                        "schema": {
                            "$ref": "#/definitions/delivery.JSONSuccessResult"
                        }
                    },
                    "400": {
                        "description": "Bad Request",
                        "schema": {
                            "$ref": "#/definitions/delivery.JSONBadReqResult"
                        }
                    },
                    "500": {
                        "description": "Internal Server Error",
                        "schema": {
                            "$ref": "#/definitions/delivery.JSONInternalResult"
                        }
                    }
                }
            },
            "delete": {
                "security": [
                    {
                        "BearerAuth": []
                    }
                ],
                "description": "Delete Product via ID",
                "consumes": [
                    "application/json"
                ],
                "produces": [
                    "application/json"
                ],
                "tags": [
                    "Product"
                ],
                "summary": "Delete Product",
                "parameters": [
                    {
                        "type": "string",
                        "description": "ID Product",
                        "name": "id",
                        "in": "path",
                        "required": true
                    }
                ],
                "responses": {
                    "200": {
                        "description": "OK",
                        "schema": {
                            "$ref": "#/definitions/delivery.JSONSuccessResult"
                        }
                    },
                    "400": {
                        "description": "Bad Request",
                        "schema": {
                            "$ref": "#/definitions/delivery.JSONBadReqResult"
                        }
                    },
                    "500": {
                        "description": "Internal Server Error",
                        "schema": {
                            "$ref": "#/definitions/delivery.JSONInternalResult"
                        }
                    }
                }
            }
        },
        "/v1/register": {
            "post": {
                "description": "register user to server with json.",
                "consumes": [
                    "application/json"
                ],
                "produces": [
                    "application/json"
                ],
                "tags": [
                    "User"
                ],
                "summary": "Register User to server",
                "parameters": [
                    {
                        "description": "User Data",
                        "name": "user",
                        "in": "body",
                        "required": true,
                        "schema": {
                            "$ref": "#/definitions/request.UserRegister"
                        }
                    }
                ],
                "responses": {
                    "200": {
                        "description": "OK",
                        "schema": {
                            "$ref": "#/definitions/delivery.JSONSuccessResult"
                        }
                    },
                    "400": {
                        "description": "Bad Request",
                        "schema": {
                            "$ref": "#/definitions/delivery.JSONBadReqResult"
                        }
                    },
                    "500": {
                        "description": "Internal Server Error",
                        "schema": {
                            "$ref": "#/definitions/delivery.JSONInternalResult"
                        }
                    }
                }
            }
        },
        "/v1/subcategory": {
            "get": {
                "description": "Get Random Tagihan Product",
                "consumes": [
                    "application/json"
                ],
                "produces": [
                    "application/json"
                ],
                "tags": [
                    "Category"
                ],
                "summary": "Get all Product w pagination",
                "responses": {
                    "200": {
                        "description": "OK",
                        "schema": {
                            "$ref": "#/definitions/delivery.JSONSuccessResult"
                        }
                    },
                    "400": {
                        "description": "Bad Request",
                        "schema": {
                            "$ref": "#/definitions/delivery.JSONBadReqResult"
                        }
                    },
                    "500": {
                        "description": "Internal Server Error",
                        "schema": {
                            "$ref": "#/definitions/delivery.JSONInternalResult"
                        }
                    }
                }
            },
            "put": {
                "security": [
                    {
                        "BearerAuth": []
                    }
                ],
                "description": "Edit subcategory via JSON",
                "consumes": [
                    "application/json"
                ],
                "produces": [
                    "application/json"
                ],
                "tags": [
                    "Category"
                ],
                "summary": "Edit subcategory",
                "parameters": [
                    {
                        "description": "User Data",
                        "name": "user",
                        "in": "body",
                        "required": true,
                        "schema": {
                            "$ref": "#/definitions/request.SubCategory"
                        }
                    }
                ],
                "responses": {
                    "200": {
                        "description": "OK",
                        "schema": {
                            "$ref": "#/definitions/delivery.JSONSuccessResult"
                        }
                    },
                    "400": {
                        "description": "Bad Request",
                        "schema": {
                            "$ref": "#/definitions/delivery.JSONBadReqResult"
                        }
                    },
                    "500": {
                        "description": "Internal Server Error",
                        "schema": {
                            "$ref": "#/definitions/delivery.JSONInternalResult"
                        }
                    }
                }
            }
        },
        "/v1/subcategory/{id}": {
            "delete": {
                "security": [
                    {
                        "BearerAuth": []
                    }
                ],
                "description": "Delete Product via ID",
                "consumes": [
                    "application/json"
                ],
                "produces": [
                    "application/json"
                ],
                "tags": [
                    "Category"
                ],
                "summary": "Delete Product",
                "parameters": [
                    {
                        "type": "string",
                        "description": "ID Category",
                        "name": "id",
                        "in": "path",
                        "required": true
                    }
                ],
                "responses": {
                    "200": {
                        "description": "OK",
                        "schema": {
                            "$ref": "#/definitions/delivery.JSONSuccessResult"
                        }
                    },
                    "400": {
                        "description": "Bad Request",
                        "schema": {
                            "$ref": "#/definitions/delivery.JSONBadReqResult"
                        }
                    },
                    "500": {
                        "description": "Internal Server Error",
                        "schema": {
                            "$ref": "#/definitions/delivery.JSONInternalResult"
                        }
                    }
                }
            }
        },
        "/v1/user": {
            "get": {
                "security": [
                    {
                        "BearerAuth": []
                    }
                ],
                "description": "Get Detail User Data.",
                "consumes": [
                    "application/json"
                ],
                "produces": [
                    "application/json"
                ],
                "tags": [
                    "User"
                ],
                "summary": "Get Detail User",
                "responses": {
                    "200": {
                        "description": "OK",
                        "schema": {
                            "$ref": "#/definitions/delivery.JSONSuccessResult"
                        }
                    },
                    "400": {
                        "description": "Bad Request",
                        "schema": {
                            "$ref": "#/definitions/delivery.JSONBadReqResult"
                        }
                    },
                    "500": {
                        "description": "Internal Server Error",
                        "schema": {
                            "$ref": "#/definitions/delivery.JSONInternalResult"
                        }
                    }
                }
            }
        },
        "/v1/user/change": {
            "post": {
                "security": [
                    {
                        "BearerAuth": []
                    }
                ],
                "description": "Change Password user to server with json.",
                "consumes": [
                    "application/json"
                ],
                "produces": [
                    "application/json"
                ],
                "tags": [
                    "User"
                ],
                "summary": "Change Password",
                "parameters": [
                    {
                        "description": "User Data",
                        "name": "user",
                        "in": "body",
                        "required": true,
                        "schema": {
                            "$ref": "#/definitions/request.PasswordUpdate"
                        }
                    }
                ],
                "responses": {
                    "200": {
                        "description": "OK",
                        "schema": {
                            "$ref": "#/definitions/delivery.JSONSuccessResult"
                        }
                    },
                    "400": {
                        "description": "Bad Request",
                        "schema": {
                            "$ref": "#/definitions/delivery.JSONBadReqResult"
                        }
                    },
                    "500": {
                        "description": "Internal Server Error",
                        "schema": {
                            "$ref": "#/definitions/delivery.JSONInternalResult"
                        }
                    }
                }
            }
        }
    },
    "definitions": {
        "delivery.JSONBadReqResult": {
            "type": "object",
            "properties": {
                "data": {},
                "meta": {
                    "type": "object",
                    "properties": {
                        "message": {
                            "type": "string",
                            "example": "failed"
                        },
                        "messages": {
                            "type": "array",
                            "items": {
                                "type": "string"
                            }
                        },
                        "status": {
                            "type": "integer",
                            "example": 400
                        }
                    }
                }
            }
        },
        "delivery.JSONInternalResult": {
            "type": "object",
            "properties": {
                "data": {},
                "meta": {
                    "type": "object",
                    "properties": {
                        "message": {
                            "type": "string",
                            "example": "error database"
                        },
                        "messages": {
                            "type": "array",
                            "items": {
                                "type": "string"
                            }
                        },
                        "status": {
                            "type": "integer",
                            "example": 500
                        }
                    }
                }
            }
        },
        "delivery.JSONSuccessResult": {
            "type": "object",
            "properties": {
                "data": {},
                "meta": {
                    "type": "object",
                    "properties": {
                        "message": {
                            "type": "string",
                            "example": "success"
                        },
                        "messages": {
                            "type": "array",
                            "items": {
                                "type": "string"
                            }
                        },
                        "status": {
                            "type": "integer",
                            "example": 200
                        }
                    }
                }
            }
        },
        "request.Category": {
            "type": "object",
            "required": [
                "name"
            ],
            "properties": {
                "name": {
                    "type": "string"
                }
            }
        },
        "request.CreateProduct": {
            "type": "object",
            "properties": {
                "category_id": {
                    "type": "integer"
                },
                "description": {
                    "type": "string"
                },
                "name": {
                    "type": "string"
                },
                "price": {
                    "type": "integer"
                },
                "stocks": {
                    "type": "integer"
                },
                "sub_category": {
                    "type": "integer"
                }
            }
        },
        "request.EditProduct": {
            "type": "object",
            "required": [
                "description",
                "id",
                "name",
                "price",
                "stocks"
            ],
            "properties": {
                "description": {
                    "type": "string"
                },
                "id": {
                    "type": "integer"
                },
                "name": {
                    "type": "string"
                },
                "price": {
                    "type": "integer"
                },
                "stocks": {
                    "type": "integer"
                }
            }
        },
        "request.PasswordUpdate": {
            "type": "object",
            "required": [
                "old_password"
            ],
            "properties": {
                "new_password": {
                    "type": "string",
                    "minLength": 8
                },
                "old_password": {
                    "type": "string"
                }
            }
        },
        "request.SubCategory": {
            "type": "object",
            "properties": {
                "id": {
                    "type": "integer"
                },
                "image_url": {
                    "type": "string"
                },
                "name": {
                    "type": "string"
                },
                "tax": {
                    "type": "integer"
                }
            }
        },
        "request.UserRegister": {
            "type": "object",
            "required": [
                "email",
                "password",
                "username"
            ],
            "properties": {
                "email": {
                    "type": "string"
                },
                "password": {
                    "type": "string"
                },
                "phone_number": {
                    "type": "string"
                },
                "username": {
                    "type": "string"
                }
            }
        }
    },
    "securityDefinitions": {
        "BearerAuth": {
            "type": "apiKey",
            "name": "Authorization",
            "in": "header"
        }
    }
}